coffee/__init__.py
coffee/__version__.py
coffee-0.0.1.dist-info/METADATA
coffee-0.0.1.dist-info/WHEEL
coffee-0.0.1.dist-info/licenses/LICENSE
coffee-0.0.1.dist-info/RECORD
