Metadata-Version: 2.1
Name: coffee
Version: 0.0.1
Summary: An HTTP API client for readable code
Project-URL: Homepage, https://github.com/jackmuskopf/coffee
Project-URL: Bug Tracker, https://github.com/jackmuskopf/coffee/issues
Author-email: Jack Muskopf <jam.muskopf@gmail.com>
License-File: LICENSE
Classifier: License :: OSI Approved :: MIT License
Classifier: Operating System :: OS Independent
Classifier: Programming Language :: Python :: 3
Requires-Python: >=3.7
